intellichat/__init__.py
intellichat/chatbot.py
intellichat-1.0.0.dist-info/LICENSE
intellichat-1.0.0.dist-info/METADATA
intellichat-1.0.0.dist-info/WHEEL
intellichat-1.0.0.dist-info/top_level.txt
intellichat-1.0.0.dist-info/RECORD
